aws_bootstrap/__init__.py
aws_bootstrap/cli.py
aws_bootstrap/config.py
aws_bootstrap/ec2.py
aws_bootstrap/gpu.py
aws_bootstrap/ssh.py
aws_bootstrap/resources/__init__.py
aws_bootstrap/resources/gpu_benchmark.py
aws_bootstrap/resources/gpu_smoke_test.ipynb
aws_bootstrap/resources/launch.json
aws_bootstrap/resources/remote_setup.sh
aws_bootstrap/resources/requirements.txt
aws_bootstrap/resources/saxpy.cu
aws_bootstrap/resources/tasks.json
aws_bootstrap/tests/__init__.py
aws_bootstrap/tests/test_cli.py
aws_bootstrap/tests/test_config.py
aws_bootstrap/tests/test_ec2.py
aws_bootstrap/tests/test_gpu.py
aws_bootstrap/tests/test_ssh_config.py
aws_bootstrap/tests/test_ssh_gpu.py
aws_bootstrap_g4dn-0.5.0.dist-info/licenses/LICENSE
aws_bootstrap_g4dn-0.5.0.dist-info/METADATA
aws_bootstrap_g4dn-0.5.0.dist-info/WHEEL
aws_bootstrap_g4dn-0.5.0.dist-info/entry_points.txt
aws_bootstrap_g4dn-0.5.0.dist-info/top_level.txt
aws_bootstrap_g4dn-0.5.0.dist-info/RECORD
