Metadata-Version: 2.4
Name: aws-bootstrap-g4dn
Version: 0.5.0
Summary: Bootstrap AWS EC2 GPU instances for hybrid local-remote development
Author: Adam Ever-Hadani
License-Expression: MIT
Project-URL: Homepage, https://github.com/promptromp/aws-bootstrap-g4dn
Project-URL: Issues, https://github.com/promptromp/aws-bootstrap-g4dn/issues
Keywords: aws,ec2,gpu,cuda,deep-learning,spot-instances,cli
Classifier: Programming Language :: Python :: 3.12
Classifier: Programming Language :: Python :: 3.13
Classifier: Programming Language :: Python :: 3.14
Requires-Python: >=3.12
License-File: LICENSE
Requires-Dist: boto3>=1.35
Requires-Dist: click>=8.1
Dynamic: license-file
